footprintsapi/__init__.py
footprintsapi/exceptions.py
footprintsapi/footprints.py
footprintsapi/mixins.py
footprintsapi/models.py
footprintsapi/requester.py
footprintsapi/utils.py
tests/__init__.py
footprintsapi-1.0.7.dist-info/LICENSE
footprintsapi-1.0.7.dist-info/METADATA
footprintsapi-1.0.7.dist-info/WHEEL
footprintsapi-1.0.7.dist-info/top_level.txt
footprintsapi-1.0.7.dist-info/RECORD
