Metadata-Version: 2.1
Name: footprintsapi
Version: 1.0.7
Summary: API wrapper for the BMC (Numara) Footprints SOAP API
Home-page: https://github.com/Jesus-E-Rodriguez/footprintsapi.git
Author: Jesus Rodriguez
Author-email: jesus_enrique@rocketmail.com
License: MIT License
Platform: UNKNOWN
Classifier: Development Status :: 5 - Production/Stable
Classifier: Intended Audience :: Developers
Classifier: Intended Audience :: Customer Service
Classifier: Intended Audience :: Information Technology
Classifier: License :: OSI Approved :: MIT License
Classifier: Operating System :: OS Independent
Classifier: Programming Language :: Python
Classifier: Programming Language :: Python :: 3.6
Classifier: Programming Language :: Python :: 3.7
Classifier: Programming Language :: Python :: 3.8
Classifier: Topic :: Software Development :: Libraries
Requires-Python: >=3.6
License-File: LICENSE
Requires-Dist: zeep (~=4.0.0)
Requires-Dist: requests (~=2.26.0)
